.gitignore
LICENSE
README.rst
conftest.py
setup.cfg
setup.py
examples/function_example.py
examples/model_example.py
sym2num/__init__.py
sym2num/function.py
sym2num/metafun.py
sym2num/model.py
sym2num/printing.py
sym2num/utils.py
sym2num/var.py
sym2num.egg-info/PKG-INFO
sym2num.egg-info/SOURCES.txt
sym2num.egg-info/dependency_links.txt
sym2num.egg-info/requires.txt
sym2num.egg-info/top_level.txt
sym2num/tests/test_model.py