Metadata-Version: 1.1
Name: sym2num
Version: 0.1.dev2
Summary: Sympy to numpy code generator.
Home-page: http://github.com/cea-ufmg/sym2num
Author: Dimas Abreu Archanjo Dutra
Author-email: dimasad@ufmg.br
License: MIT
Platform: Windows
Platform: Linux
Platform: Solaris
Platform: Mac OS-X
Platform: Unix
Classifier: Intended Audience :: Developers
Classifier: Intended Audience :: Science/Research
Classifier: License :: OSI Approved
Classifier: Operating System :: MacOS
Classifier: Operating System :: Microsoft :: Windows
Classifier: Operating System :: POSIX
Classifier: Operating System :: Unix
Classifier: Programming Language :: Python
Classifier: Programming Language :: Python :: 3
Classifier: Programming Language :: Python :: 3 :: Only
Classifier: Topic :: Scientific/Engineering
Classifier: Topic :: Software Development
